amazon_scraper_vivektyagi/__init__.py
amazon_scraper_vivektyagi/scraper.py
amazon_scraper_vivektyagi-0.1.12.dist-info/METADATA
amazon_scraper_vivektyagi-0.1.12.dist-info/WHEEL
amazon_scraper_vivektyagi-0.1.12.dist-info/top_level.txt
amazon_scraper_vivektyagi-0.1.12.dist-info/RECORD
