Metadata-Version: 2.4
Name: amazon-scraper-vivektyagi
Version: 0.1.12
Summary: A Python module to scrape product details from Amazon India using Selenium.
Author: VIVEK TYAGI
Keywords: amazon scraper selenium india
Classifier: Development Status :: 4 - Beta
Classifier: Intended Audience :: Developers
Classifier: Topic :: Software Development :: Libraries :: Python Modules
Classifier: Programming Language :: Python :: 3
Classifier: Programming Language :: Python :: 3.10
Classifier: License :: OSI Approved :: MIT License
Classifier: Operating System :: OS Independent
Requires-Python: >=3.7
Requires-Dist: beautifulsoup4>=4.12.3
Requires-Dist: selenium>=4.20.0
Dynamic: author
Dynamic: classifier
Dynamic: description
Dynamic: description-content-type
Dynamic: keywords
Dynamic: requires-dist
Dynamic: requires-python
Dynamic: summary
